api/__init__.py
api/config/__init__.py
api/config/main.py
api/config/routes.py
api/config/web.py
api/controllers/__init__.py
api/controllers/default_controller.py
config/__init__.py
config/main.py
config/routes.py
config/web.py
nailpack-flask/__init__.py
nailpack-flask/routes.py
nailpack_flask-0.1.0.dist-info/DESCRIPTION.rst
nailpack_flask-0.1.0.dist-info/METADATA
nailpack_flask-0.1.0.dist-info/RECORD
nailpack_flask-0.1.0.dist-info/WHEEL
nailpack_flask-0.1.0.dist-info/metadata.json
nailpack_flask-0.1.0.dist-info/top_level.txt
