Metadata-Version: 2.0
Name: nailpack-flask
Version: 0.1.0
Summary: Flask support for nails
Home-page: https://github.com/jamrizzi/nailpack-flask
Author: Jam Risser
Author-email: jam@jamrizzi.com
License: MIT
Keywords: mvc api rest framework flask rails trails sails development
Platform: UNKNOWN
Classifier: Development Status :: 4 - Beta
Classifier: Intended Audience :: Developers
Classifier: Framework :: Flask
Classifier: Topic :: Internet :: WWW/HTTP :: HTTP Servers
Classifier: License :: OSI Approved :: MIT License
Classifier: Programming Language :: Python :: 2
Classifier: Programming Language :: Python :: 2.7
Classifier: Programming Language :: Python :: 3
Classifier: Programming Language :: Python :: 3.3
Classifier: Programming Language :: Python :: 3.4
Classifier: Programming Language :: Python :: 3.5
Requires-Dist: aniso8601 (==1.3.0)
Requires-Dist: click (==6.7)
Requires-Dist: Flask (==0.12.2)
Requires-Dist: Flask-RESTful (==0.3.6)
Requires-Dist: itsdangerous (==0.24)
Requires-Dist: Jinja2 (==2.9.6)
Requires-Dist: MarkupSafe (==1.0)
Requires-Dist: pydash (==4.2.1)
Requires-Dist: python-dateutil (==2.6.1)
Requires-Dist: pytz (==2017.2)
Requires-Dist: six (==1.11.0)
Requires-Dist: Werkzeug (==0.12.2)
